mrg_core/__init__.py
mrg_core/_version.py
mrg_core/archive.py
mrg_core/flux_density.py
mrg_core/fovephem.py
mrg_core/imageproc.py
mrg_core/metrec2mml.py
mrg_core/mysql2sqlite.py
mrg_core/passwd.py
mrg_core/vmodb.py
mrg_core/vmodbadmin.py
mrg_core/database/__init__.py
mrg_core/database/importer.py
mrg_core/database/mots_science_db.py
mrg_core/database/vmo.sql
mrg_core/database/vmo_shared_country.sql
mrg_core/database/vmo_shared_entry_source.sql
mrg_core/database/vmo_shared_entry_status.sql
mrg_core/mml/__init__.py
mrg_core/mml/inflog.py
mrg_core/mml/metlog.py
mrg_core/mml/metrec2mml.jar
mrg_core/mml/mml.py
mrg_core/mml/reffile.py
mrg_core/mml/validator.py
mrg_core/transfer/__init__.py
mrg_core/transfer/transfer.py
mrg_core/util/__init__.py
mrg_core/util/astro.py
mrg_core/util/cmdline.py
mrg_core/util/config.py
mrg_core/util/convert.py
mrg_core/util/crypt.py
mrg_core/util/database.py
mrg_core/util/diriter.py
mrg_core/util/fileparser.py
mrg_core/util/fov.py
mrg_core/util/fov.xsl
mrg_core/util/imaging.py
mrg_core/util/interface.py
mrg_core/util/read_data_jets.py
mrg_core/util/template.py
mrg_core/util/vector.py
mrg_core/util/cmdline/__init__.py
mrg_core/util/cmdline/action.py
mrg_core/util/interfaces/__init__.py
mrg_core/util/interfaces/amos.py
mrg_core/util/interfaces/daffile.py
mrg_core/util/interfaces/kml.py
mrg_core/util/interfaces/metrec.py
mrg_core/util/interfaces/metrecinf.py
mrg_core/util/interfaces/metreclog.py
mrg_core/util/interfaces/metrecref.py
mrg_core/util/interfaces/mk.py
mrg_core/util/interfaces/mrgsql.py
mrg_core/util/interfaces/virtual.py
mrg_core-0.1.0.dist-info/DESCRIPTION.rst
mrg_core-0.1.0.dist-info/METADATA
mrg_core-0.1.0.dist-info/RECORD
mrg_core-0.1.0.dist-info/WHEEL
mrg_core-0.1.0.dist-info/entry_points.txt
mrg_core-0.1.0.dist-info/metadata.json
mrg_core-0.1.0.dist-info/top_level.txt
